{
  "badgeText": "Actively Seeking Opportunities",
  "title": "Jowel Islam Habib",
  "description": "Junior MERN Stack Developer building modern full-stack web applications using JavaScript, React.js, Next.js, Node.js, Express.js, and MongoDB. Backed by strong real-world experience in CMS development, server management, and production deployments.",
  "primaryCta": {
    "label": "Contact Me",
    "href": "#contact"
  },
  "secondaryCta": {
    "label": "Resume",
    "href": "https://jowel.bintofajjal.com/resume/Jowel_Islam_Habib_Resume.pdf"
  }
}
